ptr_claim/__init__.py
ptr_claim/__main__.py
ptr_claim/draw_map.py
ptr_claim/make_app.py
ptr_claim/prep_data.py
ptr_claim/scrape_tr.py
ptr_claim/data/Tamriel Rebuilt Province Map_2022-11-25.png
ptr_claim/data/__init.py__
ptr_claim/data/img_coords.json
ptr_claim/data/name_hints.json
ptr_claim/data/url_hints.json
ptr_claim-0.2.0.dist-info/entry_points.txt
ptr_claim-0.2.0.dist-info/LICENSE
ptr_claim-0.2.0.dist-info/WHEEL
ptr_claim-0.2.0.dist-info/METADATA
ptr_claim-0.2.0.dist-info/RECORD
