Metadata-Version: 2.1
Name: ptr-claim
Version: 0.2.0
Summary: Scrape the Tamriel Rebuilt or Project Tamriel websites and visualize claim progress.
Author-email: Kaarel Mänd <kaarel.mand@protonmail.com>
Classifier: License :: OSI Approved :: MIT License
Classifier: Framework :: Scrapy
Classifier: Framework :: Matplotlib
Classifier: Programming Language :: Python
Classifier: Programming Language :: Python :: 3
Requires-Dist: ipywidgets
Requires-Dist: kaleido
Requires-Dist: numpy
Requires-Dist: pandas
Requires-Dist: plotly
Requires-Dist: Pillow
Requires-Dist: pytesseract
Requires-Dist: python-dotenv
Requires-Dist: Scrapy
Project-URL: Home, https://github.com/kaarelmand/ptr-claim
